ctfscan/__init__.py
ctfscan/ctfscan.py
ctfscan/default.txt
CTFscan-1.4.2.dist-info/LICENSE
CTFscan-1.4.2.dist-info/METADATA
CTFscan-1.4.2.dist-info/WHEEL
CTFscan-1.4.2.dist-info/entry_points.txt
CTFscan-1.4.2.dist-info/top_level.txt
CTFscan-1.4.2.dist-info/RECORD
