Metadata-Version: 2.1
Name: CTFscan
Version: 1.4.2
Summary: a web dir scanner to make sure you won't miss something
Home-page: https://github.com/p7e4/CTFscan
Author: p7e4
Author-email: p7e4@qq.com
License: Apache 2.0
Classifier: Programming Language :: Python :: 3.8
Classifier: Programming Language :: Python :: 3.9
Classifier: Programming Language :: Python :: 3.10
Classifier: Programming Language :: Python :: 3.11
Classifier: Programming Language :: Python :: 3 :: Only
Classifier: License :: OSI Approved :: Apache Software License
Classifier: Operating System :: OS Independent
Classifier: Development Status :: 4 - Beta
Classifier: Environment :: Console
Requires-Python: >=3.8
License-File: LICENSE
Requires-Dist: arequest
